capo_tools/__init__.py
capo_tools/datasets/__init__.py
capo_tools/datasets/ETS2/__init__.py
capo_tools/datasets/ETS2/dataset.py
capo_tools/datasets/ETS2/tools.py
capo_tools/datasets/ETS2/ets2_tools/__init__.py
capo_tools/datasets/ETS2/ets2_tools/depth_file.py
capo_tools/display/__init__.py
capo_tools/display/tools/__init__.py
capo_tools/display/tools/depth_tools.py
capo_tools-0.0.3a0.dist-info/METADATA
capo_tools-0.0.3a0.dist-info/WHEEL
capo_tools-0.0.3a0.dist-info/top_level.txt
capo_tools-0.0.3a0.dist-info/RECORD
