Metadata-Version: 2.1
Name: capo_tools
Version: 0.0.3a0
Summary: Tools for CAPO Research Group projects
Home-page: https://www.caporesearch.org
Author: David Maria
Author-email: david.maria@urjc.es
Classifier: Programming Language :: Python :: 3
Classifier: Operating System :: OS Independent
